fwx.py
fwx/__init__.py
fwx-0.0.11.dist-info/LICENSE
fwx-0.0.11.dist-info/METADATA
fwx-0.0.11.dist-info/WHEEL
fwx-0.0.11.dist-info/top_level.txt
fwx-0.0.11.dist-info/RECORD
