Metadata-Version: 2.1
Name: fwx
Version: 0.0.11
Summary: fwx isn't a framework, it's a library.
Home-page: https://github.com/kerkeslager/fwx
Author: David Kerkeslager
Author-email: kerkeslager+pypi@gmail.com
License: UNKNOWN
Platform: UNKNOWN
Classifier: Programming Language :: Python :: 3
Classifier: License :: OSI Approved :: GNU Affero General Public License v3
Classifier: Development Status :: 2 - Pre-Alpha
Classifier: Intended Audience :: Developers
Classifier: Operating System :: OS Independent
